{
  "predictions_file": "results/run10a_vits/t0.3/predictions.json",
  "annotations_file": "data/annotations/test_atwood.json",
  "n_predictions_total": 9056,
  "n_gt": 228,
  "n_images": 240,
  "gate_precision": 0.01,
  "gate_recall": 0.6,
  "rows": [
    {
      "threshold": 0.3,
      "stitch": false,
      "precision": 0.0004,
      "recall": 0.0175,
      "f1": 0.0009,
      "map_50": 0.0003,
      "short_recall": 0.0,
      "medium_recall": 0.0909,
      "long_recall": 0.0098,
      "n_predictions": 9056,
      "meets_gate": false
    },
    {
      "threshold": 0.3,
      "stitch": true,
      "precision": 0.0005,
      "recall": 0.0132,
      "f1": 0.0009,
      "map_50": 0.0002,
      "short_recall": 0.0,
      "medium_recall": 0.0909,
      "long_recall": 0.0049,
      "n_predictions": 6627,
      "meets_gate": false
    },
    {
      "threshold": 0.4,
      "stitch": false,
      "precision": 0.0008,
      "recall": 0.0175,
      "f1": 0.0016,
      "map_50": 0.0003,
      "short_recall": 0.0,
      "medium_recall": 0.0909,
      "long_recall": 0.0098,
      "n_predictions": 4853,
      "meets_gate": false
    },
    {
      "threshold": 0.4,
      "stitch": true,
      "precision": 0.0011,
      "recall": 0.0175,
      "f1": 0.0021,
      "map_50": 0.0003,
      "short_recall": 0.0,
      "medium_recall": 0.0909,
      "long_recall": 0.0098,
      "n_predictions": 3530,
      "meets_gate": false
    },
    {
      "threshold": 0.5,
      "stitch": false,
      "precision": 0.0022,
      "recall": 0.0175,
      "f1": 0.0039,
      "map_50": 0.0003,
      "short_recall": 0.0,
      "medium_recall": 0.0909,
      "long_recall": 0.0098,
      "n_predictions": 1819,
      "meets_gate": false
    },
    {
      "threshold": 0.5,
      "stitch": true,
      "precision": 0.0028,
      "recall": 0.0175,
      "f1": 0.0048,
      "map_50": 0.0003,
      "short_recall": 0.0,
      "medium_recall": 0.0909,
      "long_recall": 0.0098,
      "n_predictions": 1422,
      "meets_gate": false
    },
    {
      "threshold": 0.6,
      "stitch": false,
      "precision": 0.0058,
      "recall": 0.0175,
      "f1": 0.0088,
      "map_50": 0.0003,
      "short_recall": 0.0,
      "medium_recall": 0.0909,
      "long_recall": 0.0098,
      "n_predictions": 684,
      "meets_gate": false
    },
    {
      "threshold": 0.6,
      "stitch": true,
      "precision": 0.0066,
      "recall": 0.0175,
      "f1": 0.0096,
      "map_50": 0.0003,
      "short_recall": 0.0,
      "medium_recall": 0.0909,
      "long_recall": 0.0098,
      "n_predictions": 602,
      "meets_gate": false
    },
    {
      "threshold": 0.7,
      "stitch": false,
      "precision": 0.0082,
      "recall": 0.0175,
      "f1": 0.0112,
      "map_50": 0.0003,
      "short_recall": 0.0,
      "medium_recall": 0.0909,
      "long_recall": 0.0098,
      "n_predictions": 489,
      "meets_gate": false
    },
    {
      "threshold": 0.7,
      "stitch": true,
      "precision": 0.0088,
      "recall": 0.0175,
      "f1": 0.0117,
      "map_50": 0.0003,
      "short_recall": 0.0,
      "medium_recall": 0.0909,
      "long_recall": 0.0098,
      "n_predictions": 455,
      "meets_gate": false
    },
    {
      "threshold": 0.8,
      "stitch": false,
      "precision": 0.0096,
      "recall": 0.0175,
      "f1": 0.0124,
      "map_50": 0.0003,
      "short_recall": 0.0,
      "medium_recall": 0.0909,
      "long_recall": 0.0098,
      "n_predictions": 418,
      "meets_gate": false
    },
    {
      "threshold": 0.8,
      "stitch": true,
      "precision": 0.0103,
      "recall": 0.0175,
      "f1": 0.013,
      "map_50": 0.0003,
      "short_recall": 0.0,
      "medium_recall": 0.0909,
      "long_recall": 0.0098,
      "n_predictions": 387,
      "meets_gate": false
    },
    {
      "threshold": 0.85,
      "stitch": false,
      "precision": 0.0105,
      "recall": 0.0175,
      "f1": 0.0131,
      "map_50": 0.0003,
      "short_recall": 0.0,
      "medium_recall": 0.0909,
      "long_recall": 0.0098,
      "n_predictions": 381,
      "meets_gate": false
    },
    {
      "threshold": 0.85,
      "stitch": true,
      "precision": 0.0111,
      "recall": 0.0175,
      "f1": 0.0136,
      "map_50": 0.0003,
      "short_recall": 0.0,
      "medium_recall": 0.0909,
      "long_recall": 0.0098,
      "n_predictions": 360,
      "meets_gate": false
    },
    {
      "threshold": 0.9,
      "stitch": false,
      "precision": 0.0132,
      "recall": 0.0175,
      "f1": 0.0151,
      "map_50": 0.0003,
      "short_recall": 0.0,
      "medium_recall": 0.0909,
      "long_recall": 0.0098,
      "n_predictions": 302,
      "meets_gate": false
    },
    {
      "threshold": 0.9,
      "stitch": true,
      "precision": 0.0137,
      "recall": 0.0175,
      "f1": 0.0154,
      "map_50": 0.0003,
      "short_recall": 0.0,
      "medium_recall": 0.0909,
      "long_recall": 0.0098,
      "n_predictions": 292,
      "meets_gate": false
    },
    {
      "threshold": 0.95,
      "stitch": false,
      "precision": 0.0152,
      "recall": 0.0132,
      "f1": 0.0141,
      "map_50": 0.0002,
      "short_recall": 0.0,
      "medium_recall": 0.0455,
      "long_recall": 0.0098,
      "n_predictions": 198,
      "meets_gate": false
    },
    {
      "threshold": 0.95,
      "stitch": true,
      "precision": 0.0153,
      "recall": 0.0132,
      "f1": 0.0142,
      "map_50": 0.0002,
      "short_recall": 0.0,
      "medium_recall": 0.0455,
      "long_recall": 0.0098,
      "n_predictions": 196,
      "meets_gate": false
    }
  ]
}